ebc939d605126d411c4cd6f80aaa4b10/__init__.py
ebc939d605126d411c4cd6f80aaa4b10/animev2.py
ebc939d605126d411c4cd6f80aaa4b10/app.py
ebc939d605126d411c4cd6f80aaa4b10/flux.py
ebc939d605126d411c4cd6f80aaa4b10/flux_pro.py
ebc939d605126d411c4cd6f80aaa4b10/klogin.py
ebc939d605126d411c4cd6f80aaa4b10/kreg.py
ebc939d605126d411c4cd6f80aaa4b10/linearv1.py
ebc939d605126d411c4cd6f80aaa4b10/logs.py
ebc939d605126d411c4cd6f80aaa4b10/pic_login.py
ebc939d605126d411c4cd6f80aaa4b10/pic_reg.py
ebc939d605126d411c4cd6f80aaa4b10/ponyv6.py
ebc939d605126d411c4cd6f80aaa4b10/realisticv2.py
ebc939d605126d411c4cd6f80aaa4b10/remove.py
ebc939d605126d411c4cd6f80aaa4b10/runway_image2_to_video.py
ebc939d605126d411c4cd6f80aaa4b10/runway_image_to_video.py
ebc939d605126d411c4cd6f80aaa4b10/runway_upload_image.py
ebc939d605126d411c4cd6f80aaa4b10/runway_upload_image2.py
ebc939d605126d411c4cd6f80aaa4b10/upscaler.py
gradio_uploader_12559-1.9.0.dist-info/LICENSE
gradio_uploader_12559-1.9.0.dist-info/METADATA
gradio_uploader_12559-1.9.0.dist-info/WHEEL
gradio_uploader_12559-1.9.0.dist-info/top_level.txt
gradio_uploader_12559-1.9.0.dist-info/RECORD
